simplified_regex/__init__.py
simplified_regex/__main__.py
simplified_regex/cli.py
simplified_regex-1.0.dist-info/LICENSE
simplified_regex-1.0.dist-info/METADATA
simplified_regex-1.0.dist-info/WHEEL
simplified_regex-1.0.dist-info/entry_points.txt
simplified_regex-1.0.dist-info/top_level.txt
simplified_regex-1.0.dist-info/RECORD
