Metadata-Version: 2.1
Name: simplified_regex
Version: 1.0
Summary: A tool that simplifies RegEx extremly!
Home-page: https://github.com/d-i-projects/simplified_regex
Download-URL: https://github.com/D-I-Projects/simplified_regex/archive/refs/tags/v1.0.tar.gz
Author: D&I
Author-email: di.projects.help@gmail.com
License: MIT
Keywords: simplified_regex,regex,simple
Classifier: Development Status :: 5 - Production/Stable
Classifier: Intended Audience :: Developers
Classifier: Topic :: Software Development :: Libraries
Classifier: License :: OSI Approved :: MIT License
Classifier: Programming Language :: Python :: 3.9
Requires-Python: >=3.9
License-File: LICENSE
